velovi/__init__.py
velovi/_constants.py
velovi/_model.py
velovi/_module.py
velovi/_utils.py
velovi-0.3.1.dist-info/LICENSE
velovi-0.3.1.dist-info/METADATA
velovi-0.3.1.dist-info/WHEEL
velovi-0.3.1.dist-info/RECORD
