Metadata-Version: 2.1
Name: velovi
Version: 0.3.1
Summary: Estimation of RNA velocity with variational inference.
Home-page: https://github.com/YosefLab/velovi
License: BSD-3-Clause
Author: Adam Gayoso
Author-email: adamgayoso@berkeley.edu
Requires-Python: >=3.9,<4.0
Classifier: Development Status :: 4 - Beta
Classifier: Intended Audience :: Science/Research
Classifier: License :: OSI Approved :: BSD License
Classifier: Natural Language :: English
Classifier: Operating System :: MacOS :: MacOS X
Classifier: Operating System :: Microsoft :: Windows
Classifier: Operating System :: POSIX :: Linux
Classifier: Programming Language :: Python :: 3
Classifier: Programming Language :: Python :: 3.9
Classifier: Programming Language :: Python :: 3.10
Classifier: Programming Language :: Python :: 3.11
Classifier: Programming Language :: Python :: 3.10
Classifier: Programming Language :: Python :: 3.11
Classifier: Programming Language :: Python :: 3.9
Classifier: Topic :: Scientific/Engineering :: Bio-Informatics
Provides-Extra: dev
Provides-Extra: docs
Provides-Extra: tutorials
Requires-Dist: anndata (>=0.7.5)
Requires-Dist: black (>=20.8b1) ; extra == "dev"
Requires-Dist: codecov (>=2.0.8) ; extra == "dev"
Requires-Dist: importlib-metadata (>=1.0,<2.0) ; python_version < "3.8"
Requires-Dist: ipykernel ; extra == "docs"
Requires-Dist: ipython (>=7.1.1) ; extra == "docs" or extra == "docs"
Requires-Dist: jupyter (>=1.0) ; extra == "dev"
Requires-Dist: myst-nb ; extra == "docs"
Requires-Dist: pre-commit (>=2.7.1) ; extra == "dev"
Requires-Dist: pytest (>=4.4) ; extra == "dev"
Requires-Dist: pytest-cov ; extra == "dev"
Requires-Dist: python-igraph
Requires-Dist: ruff ; extra == "dev"
Requires-Dist: scanpy (>=1.6) ; extra == "dev" or extra == "tutorials"
Requires-Dist: scanpydoc (>=0.5) ; extra == "docs"
Requires-Dist: scikit-learn (>=0.21.2)
Requires-Dist: scvelo (>=0.2.5)
Requires-Dist: scvi-tools (>=1.0.0)
Requires-Dist: sphinx (>=4.1) ; extra == "docs"
Requires-Dist: sphinx-autodoc-typehints
Requires-Dist: sphinx-book-theme (>=1.0.0) ; extra == "docs"
Requires-Dist: sphinx-copybutton ; extra == "docs"
Requires-Dist: sphinxcontrib-bibtex ; extra == "docs"
Project-URL: Documentation, https://scvi-tools.org
